exa/common/__init__.py
exa/common/py.typed
exa/common/api/__init__.py
exa/common/api/proto_serialization/__init__.py
exa/common/api/proto_serialization/_parameter.py
exa/common/api/proto_serialization/array.py
exa/common/api/proto_serialization/datum.py
exa/common/api/proto_serialization/nd_sweep.py
exa/common/api/proto_serialization/sequence.py
exa/common/api/proto_serialization/setting_node.py
exa/common/control/__init__.py
exa/common/control/sweep/__init__.py
exa/common/control/sweep/sweep.py
exa/common/control/sweep/sweep_values.py
exa/common/control/sweep/option/__init__.py
exa/common/control/sweep/option/center_span_base_options.py
exa/common/control/sweep/option/center_span_options.py
exa/common/control/sweep/option/constants.py
exa/common/control/sweep/option/fixed_options.py
exa/common/control/sweep/option/option_converter.py
exa/common/control/sweep/option/start_stop_base_options.py
exa/common/control/sweep/option/start_stop_options.py
exa/common/control/sweep/option/sweep_options.py
exa/common/data/__init__.py
exa/common/data/base_model.py
exa/common/data/parameter.py
exa/common/data/setting_node.py
exa/common/data/settingnode_v2.html.jinja2
exa/common/data/value.py
exa/common/errors/__init__.py
exa/common/errors/exa_error.py
exa/common/errors/station_control_errors.py
exa/common/helpers/__init__.py
exa/common/helpers/data_helper.py
exa/common/helpers/deprecation.py
exa/common/helpers/json_helper.py
exa/common/helpers/numpy_helper.py
exa/common/helpers/software_version_helper.py
exa/common/helpers/yaml_helper.py
exa/common/logger/__init__.py
exa/common/logger/logger.py
exa/common/qcm_data/__init__.py
exa/common/qcm_data/chad_model.py
exa/common/qcm_data/chip_layout.py
exa/common/qcm_data/chip_topology.py
exa/common/qcm_data/file_adapter.py
exa/common/qcm_data/immutable_base_model.py
exa/common/qcm_data/qcm_data_client.py
exa/common/sweep/__init__.py
exa/common/sweep/database_serialization.py
exa/common/sweep/util.py
iqm_exa_common-27.4.3.dist-info/LICENSE.txt
iqm_exa_common-27.4.3.dist-info/METADATA
iqm_exa_common-27.4.3.dist-info/WHEEL
iqm_exa_common-27.4.3.dist-info/top_level.txt
iqm_exa_common-27.4.3.dist-info/RECORD
