Metadata-Version: 2.1
Name: iqm-exa-common
Version: 27.4.3
Summary: Framework for control and measurement of superconducting qubits: common library
Author-email: IQM Finland Oy <info@meetiqm.com>
License: Apache License
Project-URL: Documentation, https://docs.meetiqm.com/iqm-exa-common/
Project-URL: Homepage, https://pypi.org/project/iqm-exa-common/
Classifier: Development Status :: 4 - Beta
Classifier: Programming Language :: Python :: 3 :: Only
Classifier: Topic :: Scientific/Engineering :: Physics
Classifier: Intended Audience :: Science/Research
Requires-Python: >=3.11
License-File: LICENSE.txt
Requires-Dist: iqm-data-definitions <3.0,>=2.18
Requires-Dist: numpy <3.0,>=1.26.4
Requires-Dist: pydantic <3.0,>=2.10.4
Requires-Dist: python-dotenv ==0.21.1
Requires-Dist: xarray ==2024.10.0
Requires-Dist: requests ==2.32.3
Requires-Dist: types-requests
Requires-Dist: ruamel-yaml ==0.17.32
Requires-Dist: ruamel-yaml-clib ==0.2.8
Requires-Dist: jinja2 ==3.0.3
Requires-Dist: six ==1.16.0
Requires-Dist: types-six
